tox_ini_fmt/__init__.py
tox_ini_fmt/__main__.py
tox_ini_fmt/cli.py
tox_ini_fmt/py.typed
tox_ini_fmt/version.py
tox_ini_fmt/formatter/__init__.py
tox_ini_fmt/formatter/requires.py
tox_ini_fmt/formatter/section_order.py
tox_ini_fmt/formatter/test_env.py
tox_ini_fmt/formatter/tox_section.py
tox_ini_fmt/formatter/util.py
tox_ini_fmt-1.7.1.dist-info/METADATA
tox_ini_fmt-1.7.1.dist-info/WHEEL
tox_ini_fmt-1.7.1.dist-info/entry_points.txt
tox_ini_fmt-1.7.1.dist-info/licenses/LICENSE.txt
tox_ini_fmt-1.7.1.dist-info/RECORD
