Metadata-Version: 2.4
Name: tox-ini-fmt
Version: 1.7.1
Summary: tox is a generic virtualenv management and test command line tool
Project-URL: Documentation, https://tox.wiki
Project-URL: Homepage, https://github.com/tox-dev/tox-ini-fmt/blob/main/README.md#tox-ini-fmt
Project-URL: Release Notes, https://github.com/tox-dev/tox-ini-fmt/blob/main/CHANGELOG.md
Project-URL: Source, https://github.com/tox-dev/tox-ini-fmt
Project-URL: Tracker, https://github.com/tox-dev/tox-ini-fmt/issues
Maintainer-email: Bernát Gábor <gaborjbernat@gmail.com>
License-Expression: MIT
License-File: LICENSE.txt
Keywords: environments,isolated,testing,virtual
Classifier: Development Status :: 5 - Production/Stable
Classifier: Framework :: tox
Classifier: Intended Audience :: Developers
Classifier: License :: OSI Approved :: MIT License
Classifier: Operating System :: MacOS :: MacOS X
Classifier: Operating System :: Microsoft :: Windows
Classifier: Operating System :: POSIX
Classifier: Programming Language :: Python :: 3 :: Only
Classifier: Programming Language :: Python :: 3.10
Classifier: Programming Language :: Python :: 3.11
Classifier: Programming Language :: Python :: 3.12
Classifier: Programming Language :: Python :: 3.13
Classifier: Programming Language :: Python :: 3.14
Classifier: Topic :: Software Development :: Libraries
Classifier: Topic :: Software Development :: Testing
Classifier: Topic :: Utilities
Requires-Python: >=3.10
Requires-Dist: packaging>=25
Provides-Extra: testing
Requires-Dist: covdefaults>=2.3; extra == 'testing'
Requires-Dist: pytest-cov>=7; extra == 'testing'
Requires-Dist: pytest>=8.4.2; extra == 'testing'
